{
  "artifact_id": "d2450181-bb97-4165-a82e-e90ad3475b9e",
  "step_number": 3,
  "timestamp": "2026-02-04T22:45:24.248175+00:00",
  "era": 1,
  "success": true,
  "metadata": {
    "global_best_practices": {
      "frameworks": [
        "TOGAF Standard 10th Edition",
        "Federal Enterprise Architecture Framework (FEAF)",
        "ISO/IEC/IEEE 42010:2011",
        "California Enterprise Architecture Glossary",
        "KPMG Modern EA Governance Framework",
        "ExecLayer Policy-Enforced Execution Layer",
        "Clean Core Principles",
        "Layered Enterprise Architecture (LEAD)",
        "IEEE 1471: Recommended Practice for Architecture Description",
        "ISO/IEC 12207: Systems and Software Engineering",
        "NIST Cybersecurity Framework"
      ],
      "principles": [
        "Immutable core architecture",
        "Policy-enforced execution",
        "Closed-loop governance",
        "Evidence-based decision making"
      ],
      "patterns": [
        "Multi-layer enforcement",
        "Subsystem binding",
        "Event-driven governance",
        "Automated remediation"
      ]
    }
  },
  "execution_time_ms": 0,
  "violations_count": 0,
  "artifacts_generated": [
    "global_best_practices_model.json"
  ],
  "sha256_hash": "979d23ae7cb11a743601fd09bdb48f41421f48bbbd5a03ae2820800738b41e3e",
  "canonical_hash": "979d23ae7cb11a743601fd09bdb48f41421f48bbbd5a03ae2820800738b41e3e",
  "canonicalization_version": "1.0",
  "canonicalization_method": "JCS+LayeredSorting",
  "hash_chain": {
    "self": "979d23ae7cb11a743601fd09bdb48f41421f48bbbd5a03ae2820800738b41e3e",
    "parent": null,
    "merkle_root": null
  }
}